{"inkVersion":19,"root":[["ev","str","^Smile","/str","/ev",{"VAR=":"AlexSprite","re":true},"^It's an early Saturday morning.","\n","^...","\n","^...","\n","^...","\n","^...","\n","^Alex heads to  the mall","\n","^As Alex enters the complex, ","ev",{"VAR?":"pron_Alex"},"out","/ev","^ sees some people roaming around... Which is odd considering the time of day...","\n","ev","str","^Doubtful","/str","/ev",{"VAR=":"AlexSprite","re":true},"^Alex is considering what store to visit.","\n",["ev",{"^->":"0.33.$r1"},{"temp=":"$r"},"str",{"->":".^.s"},[{"#n":"$r1"}],"/str","/ev",{"*":"0.c-0","flg":18},{"s":["^...",{"->":"$r","var":true},null]}],["ev",{"^->":"0.34.$r1"},{"temp=":"$r"},"str",{"->":".^.s"},[{"#n":"$r1"}],"/str","/ev",{"*":"0.c-1","flg":18},{"s":["^...",{"->":"$r","var":true},null]}],{"c-0":["ev",{"^->":"0.c-0.$r2"},"/ev",{"temp=":"$r"},{"->":"0.33.s"},[{"#n":"$r2"}],"\n","ev","str","^Cloud 9 Super Store","/str","/ev",{"VAR=":"StoreName","re":true},{"->":"Store"},{"->":"0.g-0"},{"#f":5}],"c-1":["ev",{"^->":"0.c-1.$r2"},"/ev",{"temp=":"$r"},{"->":"0.34.s"},[{"#n":"$r2"}],"\n","ev","str","^Gnome Depot","/str","/ev",{"VAR=":"StoreName","re":true},{"->":"Store"},{"->":"0.g-0"},{"#f":5}],"g-0":["done",{"#f":5}]}],"done",{"Store":["^Alex enters ","ev",{"VAR?":"StoreName"},"out","/ev","^. ","ev",{"VAR?":"Pron_Alex"},"out","/ev","^ sees some people already roaming the corridors, enjoying the items on sale.","\n","^Some employees are also roaming around, helping costumers and replenishing stock.","\n","ev","str","^Smile","/str","/ev",{"VAR=":"AlexSprite","re":true},"^...","\n","^...","\n","^Alex looks carefully at the aisle directory and picks up 3 ","ev",{"VAR?":"pron_Alex"},"out","/ev","^ finds appropriate.","\n",{"->":"Aisle_Selection"},{"#f":1}],"Aisle_Selection":[[["ev","visit",3,"MIN","/ev","ev","du",0,"==","/ev",{"->":".^.s0","c":true},"ev","du",1,"==","/ev",{"->":".^.s1","c":true},"ev","du",2,"==","/ev",{"->":".^.s2","c":true},"ev","du",3,"==","/ev",{"->":".^.s3","c":true},"nop",{"s0":["pop","^...",{"->":".^.^.29"},null],"s1":["pop","^...",{"->":".^.^.29"},null],"s2":["pop","^...",{"->":".^.^.29"},null],"s3":["pop",{"->":".^.^.29"},null],"#f":5}],"\n","ev","str","^Doubtful","/str","/ev",{"VAR=":"AlexSprite","re":true},["ev",{"^->":"Aisle_Selection.0.8.$r1"},{"temp=":"$r"},"str",{"->":".^.s"},[{"#n":"$r1"}],"/str","/ev",{"*":".^.^.c-0","flg":18},{"s":["^...",{"->":"$r","var":true},null]}],["ev",{"^->":"Aisle_Selection.0.9.$r1"},{"temp=":"$r"},"str",{"->":".^.s"},[{"#n":"$r1"}],"/str","/ev",{"*":".^.^.c-1","flg":18},{"s":["^...",{"->":"$r","var":true},null]}],["ev",{"^->":"Aisle_Selection.0.10.$r1"},{"temp=":"$r"},"str",{"->":".^.s"},[{"#n":"$r1"}],"/str","/ev",{"*":".^.^.c-2","flg":18},{"s":["^...",{"->":"$r","var":true},null]}],["ev",{"^->":"Aisle_Selection.0.11.$r1"},{"temp=":"$r"},"str",{"->":".^.s"},[{"#n":"$r1"}],"/str",{"VAR?":"visitA1"},{"VAR?":"visitA2"},"||",{"VAR?":"visitA3"},"||","/ev",{"*":".^.^.c-3","flg":19},{"s":["^...",{"->":"$r","var":true},null]}],{"*":".^.c-4","flg":24},{"c-0":["ev",{"^->":"Aisle_Selection.0.c-0.$r2"},"/ev",{"temp=":"$r"},{"->":".^.^.8.s"},[{"#n":"$r2"}],"\n","ev",1,"/ev",{"VAR=":"visitA1","re":true},"^Alex heads into the Office Materials aisle and looks around.","\n","^All of a sudden a store employee that has been restocking shelves approaches ","ev",{"VAR?":"poss_pron_Alex"},"out","/ev","^.","\n","^\"Hello!\" He says, a wide smile on his lips. \"Do you need help?\"","\n",["ev","str","^...","/str","/ev",{"*":".^.c-0","flg":20},"ev","str","^...","/str","/ev",{"*":".^.c-1","flg":20},{"c-0":["\n","^\"I'm not sure.\" Alex tells him, with an unsure look on ","ev",{"VAR?":"poss_pron_Alex"},"out","/ev","^ face.","\n","^\"Well, we are having a huge sale on canvases... Are you perchance an artist?\" He asks Alex.","\n","^...","\n","^Alex looks at the price of the canvases and even ","ev",{"VAR?":"pron_Alex"},"out","/ev","^, who has no idea what the usual price of the item is impressed.","\n","ev",{"VAR?":"pron_Alex"},"out","/ev","^ looks at the employee satisfied.","\n","ev","str","^Happy","/str","/ev",{"VAR=":"AlexSprite","re":true},"^\"Thanks!\" ","ev",{"VAR?":"pron_Alex"},"out","/ev","^ says, to which the employee answers with a triumphant smile and a thumbs up!","\n","^...","\n","^...","\n","^Alex picks up the phone, typing something... A text, perhaps?","\n","^...","\n","^Alex puts the phone away with a vigorous shake of the head.","\n","^...","\n","^Alex seems conflicted.","\n",{"->":".^.^.^.^.^"},{"#f":5}],"c-1":["\n","^\"I'm looking for a birthday gift.\" Alex tells him.","\n","^\"Ohh... Someone special?\" He asks with a mock tone.","\n","^\"Yeah... I guess you could say that... It's for my housemate.\" ","ev",{"VAR?":"pron_Alex"},"out","/ev","^ answers.","\n","^\"So... What are they like? What do they like?\"","\n","^...","\n","^\"I guess she likes... Arts?\"","\n","^The employee seems delighted with Alex's answer. \"Well, we are having a huge sale on canvases...\"","\n","^Alex looks at the prices of the items the employee pointed out.","\n","^...","\n","ev",{"VAR?":"pron_Alex"},"out","/ev","^ looks at the employee satisfied.","\n","ev","str","^Happy","/str","/ev",{"VAR=":"AlexSprite","re":true},"^\"Thanks!\" ","ev",{"VAR?":"pron_Alex"},"out","/ev","^ says, to which the employee answers with a triumphant smile and a thumbs up!","\n","^...","\n","^Alex picks up the phone, typing something... A text, perhaps?","\n","^...","\n","^Alex puts the phone away with a vigorous shake of the head.","\n","^...","\n","^Alex seems conflicted.","\n",{"->":".^.^.^.^.^"},{"#f":5}]}],{"#f":5}],"c-1":["ev",{"^->":"Aisle_Selection.0.c-1.$r2"},"/ev",{"temp=":"$r"},{"->":".^.^.9.s"},[{"#n":"$r2"}],"\n","ev",1,"/ev",{"VAR=":"visitA2","re":true},"^Alex heads in the direction of the sports aisle.","\n","^There are shelves on shelves on shelves of different types of balls.","\n","^Soccer balls, Football balls, tennis balls, golf balls... Colorful bouncy balls.","\n","^There are also many different types of shoes for different kinds of sports.","\n","ev",{"VAR?":"visitA1"},"/ev",[{"->":".^.b","c":true},{"b":["^...",{"->":".^.^.^.23"},null]}],"nop","\n","^...","\n","^...","\n","^Alex nods at no one.","\n",{"->":".^.^.^"},{"#f":5}],"c-2":["ev",{"^->":"Aisle_Selection.0.c-2.$r2"},"/ev",{"temp=":"$r"},{"->":".^.^.10.s"},[{"#n":"$r2"}],"\n","ev",1,"/ev",{"VAR=":"visitA3","re":true},"^Alex heads in the direction of the books aisle.","\n","^...","\n","^...","\n","^...","\n","^...","\n","^Alex seems to have reached a conclusion and is satisfied.","\n",{"->":".^.^.^"},{"#f":5}],"c-3":["ev",{"^->":"Aisle_Selection.0.c-3.$r2"},"/ev",{"temp=":"$r"},{"->":".^.^.11.s"},[{"#n":"$r2"}],"\n",{"->":"BuyItem"},{"#f":5}],"c-4":[{"->":"BuyItem"},"\n",{"#f":5}]}],{"#f":1}],"BuyItem":[["^...","\n",["ev",{"^->":"BuyItem.0.2.$r1"},{"temp=":"$r"},"str",{"->":".^.s"},[{"#n":"$r1"}],"/str",{"VAR?":"visitA1"},"/ev",{"*":".^.^.c-0","flg":19},{"s":["^Alex has decided what to buy.",{"->":"$r","var":true},null]}],["ev",{"^->":"BuyItem.0.3.$r1"},{"temp=":"$r"},"str",{"->":".^.s"},[{"#n":"$r1"}],"/str",{"VAR?":"visitA2"},"/ev",{"*":".^.^.c-1","flg":19},{"s":["^Alex has decided what to buy.",{"->":"$r","var":true},null]}],["ev",{"^->":"BuyItem.0.4.$r1"},{"temp=":"$r"},"str",{"->":".^.s"},[{"#n":"$r1"}],"/str",{"VAR?":"visitA3"},"/ev",{"*":".^.^.c-2","flg":19},{"s":["^Alex has decided what to buy.",{"->":"$r","var":true},null]}],{"c-0":["ev",{"^->":"BuyItem.0.c-0.$r2"},"/ev",{"temp=":"$r"},{"->":".^.^.2.s"},[{"#n":"$r2"}],"\n","ev",1,"/ev",{"VAR=":"chosen","re":true},{"->":"Payment"},{"#f":5}],"c-1":["ev",{"^->":"BuyItem.0.c-1.$r2"},"/ev",{"temp=":"$r"},{"->":".^.^.3.s"},[{"#n":"$r2"}],"\n","ev",2,"/ev",{"VAR=":"chosen","re":true},{"->":"Payment"},{"#f":5}],"c-2":["ev",{"^->":"BuyItem.0.c-2.$r2"},"/ev",{"temp=":"$r"},{"->":".^.^.4.s"},[{"#n":"$r2"}],"\n","ev",3,"/ev",{"VAR=":"chosen","re":true},{"->":"Payment"},{"#f":5}]}],{"#f":1}],"Payment":[["ev","str","^Smile","/str","/ev",{"VAR=":"AlexSprite","re":true},"^Alex exits the store with ","ev",{"VAR?":"poss_pron_Alex"},"out","/ev","^ purchase.","\n","^...","\n","^...","\n","ev","str","^...","/str","/ev",{"*":".^.c-0","flg":20},"ev","str","^...","/str","/ev",{"*":".^.c-1","flg":20},{"c-0":["\n","^...","\n","^...","\n",["ev","str","^...","/str","/ev",{"*":".^.c-0","flg":20},"ev","str","^...","/str","/ev",{"*":".^.c-1","flg":20},"ev","str","^...","/str","/ev",{"*":".^.c-2","flg":20},{"c-0":["\n","^...","\n","^Alex heads in into the bakery at the mall... What could ","ev",{"VAR?":"pron_Alex"},"out","/ev","^ possibly be buying there?","\n","end",{"#f":5}],"c-1":["\n","^...","\n","^Alex heads in into the bakery at the mall... What could ","ev",{"VAR?":"pron_Alex"},"out","/ev","^ possibly be buying there?","\n","end",{"#f":5}],"c-2":["\n","^...","\n","^Alex heads in into the bakery at the mall... What could ","ev",{"VAR?":"pron_Alex"},"out","/ev","^ possibly be buying there?","\n","end",{"#f":5}]}],{"#f":5}],"c-1":["\n","^...","\n","^Alex heads hope straight away.","\n","end",{"#f":5}]}],{"#f":1}],"global decl":["ev",0,{"VAR=":"visitA1"},0,{"VAR=":"visitA2"},0,{"VAR=":"visitA3"},0,{"VAR=":"chosen"},"str","^","/str",{"VAR=":"StoreName"},"str","^they","/str",{"VAR=":"pron_Alex"},"str","^They","/str",{"VAR=":"Pron_Alex"},"str","^their","/str",{"VAR=":"poss_pron_Alex"},"str","^they","/str",{"VAR=":"pron_Jesse"},"str","^They","/str",{"VAR=":"Pron_Jesse"},"str","^their","/str",{"VAR=":"poss_pron_Jesse"},"str","^Smile","/str",{"VAR=":"AlexSprite"},"/ev","end",null],"#f":1}],"listDefs":{}}